ipsl_ncdiff/__init__.py
ipsl_ncdiff/cli.py
ipsl_ncdiff/diff.py
ipsl_ncdiff/output.py
ipsl_ncdiff/py.typed
ipsl_ncdiff/tolerance.py
ipsl_ncdiff/transformation.py
ipsl_ncdiff/comparator/__init__.py
ipsl_ncdiff/comparator/value.py
ipsl_ncdiff/loader/__init__.py
ipsl_ncdiff/loader/_h5netcdf.py
ipsl_ncdiff/loader/_netcdf4.py
ipsl_ncdiff/loader/auto.py
ipsl_ncdiff/model/__init__.py
ipsl_ncdiff/model/dataset.py
ipsl_ncdiff/model/diff.py
ipsl_ncdiff/model/dimension.py
ipsl_ncdiff/model/variable.py
ipsl_ncdiff-0.1.4.dist-info/METADATA
ipsl_ncdiff-0.1.4.dist-info/WHEEL
ipsl_ncdiff-0.1.4.dist-info/entry_points.txt
ipsl_ncdiff-0.1.4.dist-info/RECORD
