Metadata-Version: 2.4
Name: ipsl-ncdiff
Version: 0.1.4
Summary: Find differences between two NetCDF files
Author-email: Patryk Kiepas <patryk.kiepas@polytechnique.edu>
Classifier: Programming Language :: Python :: 3 :: Only
Classifier: Programming Language :: Python :: 3.12
Classifier: Programming Language :: Python :: 3.13
Classifier: Programming Language :: Python :: 3.14
Requires-Python: >=3.12
Requires-Dist: h5netcdf>=1.6.1
Requires-Dist: more-itertools>=10.7
Requires-Dist: netcdf4>=1.7.3
Requires-Dist: prettytable>=3.16
